<?xml version='1.0' encoding='UTF-8'?>
<data>
	<annotations>
		<entity>
			<id>0@regex</id>
			<type>PreAnnotation</type>
			<span>14,28</span>
		</entity>
		<entity>
			<id>1@regex</id>
			<type>PreAnnotation</type>
			<span>87,91</span>
		</entity>
		<entity>
			<id>2@regex</id>
			<type>PreAnnotation</type>
			<span>93,103</span>
		</entity>
		<entity>
			<id>3@regex</id>
			<type>PreAnnotation</type>
			<span>159,167</span>
		</entity>
		<entity>
			<id>4@regex</id>
			<type>PreAnnotation</type>
			<span>186,194</span>
		</entity>
		<entity>
			<id>5@regex</id>
			<type>PreAnnotation</type>
			<span>399,402</span>
		</entity>
		<entity>
			<id>6@regex</id>
			<type>PreAnnotation</type>
			<span>744,750</span>
		</entity>
	</annotations>
</data>
