<?xml version='1.0' encoding='UTF-8'?>
<data>
	<annotations>
		<entity>
			<id>0@regex</id>
			<type>PreAnnotation</type>
			<span>14,18</span>
		</entity>
		<entity>
			<id>1@regex</id>
			<type>PreAnnotation</type>
			<span>20,39</span>
		</entity>
		<entity>
			<id>2@regex</id>
			<type>PreAnnotation</type>
			<span>54,58</span>
		</entity>
		<entity>
			<id>3@regex</id>
			<type>PreAnnotation</type>
			<span>70,89</span>
		</entity>
		<entity>
			<id>4@regex</id>
			<type>PreAnnotation</type>
			<span>159,163</span>
		</entity>
		<entity>
			<id>5@regex</id>
			<type>PreAnnotation</type>
			<span>578,584</span>
		</entity>
		<entity>
			<id>6@regex</id>
			<type>PreAnnotation</type>
			<span>743,752</span>
		</entity>
		<entity>
			<id>7@regex</id>
			<type>PreAnnotation</type>
			<span>841,846</span>
		</entity>
		<entity>
			<id>8@regex</id>
			<type>PreAnnotation</type>
			<span>1384,1391</span>
		</entity>
		<entity>
			<id>9@regex</id>
			<type>PreAnnotation</type>
			<span>1541,1544</span>
		</entity>
		<entity>
			<id>10@regex</id>
			<type>PreAnnotation</type>
			<span>1873,1878</span>
		</entity>
		<entity>
			<id>11@regex</id>
			<type>PreAnnotation</type>
			<span>1912,1917</span>
		</entity>
		<entity>
			<id>12@regex</id>
			<type>PreAnnotation</type>
			<span>2607,2611</span>
		</entity>
		<entity>
			<id>13@regex</id>
			<type>PreAnnotation</type>
			<span>2831,2837</span>
		</entity>
		<entity>
			<id>14@regex</id>
			<type>PreAnnotation</type>
			<span>2908,2915</span>
		</entity>
		<entity>
			<id>15@regex</id>
			<type>PreAnnotation</type>
			<span>3024,3028</span>
		</entity>
		<entity>
			<id>16@regex</id>
			<type>PreAnnotation</type>
			<span>3160,3163</span>
		</entity>
		<entity>
			<id>17@regex</id>
			<type>PreAnnotation</type>
			<span>3200,3204</span>
		</entity>
		<entity>
			<id>18@regex</id>
			<type>PreAnnotation</type>
			<span>3308,3312</span>
		</entity>
		<entity>
			<id>19@regex</id>
			<type>PreAnnotation</type>
			<span>3341,3345</span>
		</entity>
		<entity>
			<id>20@regex</id>
			<type>PreAnnotation</type>
			<span>3369,3375</span>
		</entity>
		<entity>
			<id>21@regex</id>
			<type>PreAnnotation</type>
			<span>3788,3792</span>
		</entity>
		<entity>
			<id>22@regex</id>
			<type>PreAnnotation</type>
			<span>4148,4156</span>
		</entity>
	</annotations>
</data>
